{"tickers": [{"symbol": "BTC/USDT", "last": 90811.96, "volume": 3363628120.446029, "change": 1.172}, {"symbol": "ETH/USDT", "last": 3169.13, "volume": 1665851278.056617, "change": 2.597}, {"symbol": "BNB/USDT", "last": 627.53, "volume": 325666674.91265, "change": 1.855}, {"symbol": "NEO/USDT", "last": 12.62, "volume": 10236589.9405, "change": 11.189}, {"symbol": "LTC/USDT", "last": 88.58, "volume": 143595912.64286, "change": 3.048}, {"symbol": "QTUM/USDT", "last": 3.125, "volume": 5654292.1642, "change": 12.613}, {"symbol": "ADA/USDT", "last": 0.7735, "volume": 756918102.02162, "change": 15.845}, {"symbol": "XRP/USDT", "last": 1.1566, "volume": 1755293478.3738, "change": 29.229}, {"symbol": "EOS/USDT", "last": 0.6668, "volume": 41702735.36358, "change": 13.498}, {"symbol": "TUSD/USDT", "last": 0.9962, "volume": 2736731.2558, "change": -0.13}, {"symbol": "IOTA/USDT", "last": 0.1651, "volume": 11192817.2532, "change": 12.619}, {"symbol": "XLM/USDT", "last": 0.178, "volume": 95416623.0772, "change": 25.264}, {"symbol": "ONT/USDT", "last": 0.2222, "volume": 2040138.2958, "change": 9.35}, {"symbol": "TRX/USDT", "last": 0.2012, "volume": 134384264.104395, "change": 7.078}, {"symbol": "ETC/USDT", "last": 25.61, "volume": 66299189.0176, "change": 11.834}, {"symbol": "ICX/USDT", "last": 0.1576, "volume": 1536487.258, "change": 7.577}, {"symbol": "NULS/USDT", "last": 0.3359, "volume": 1659544.7669, "change": 0.901}, {"symbol": "VET/USDT", "last": 0.0294, "volume": 21303573.563497, "change": 18.453}, {"symbol": "USDC/USDT", "last": 0.9996, "volume": 982421035.2704, "change": -0.02}, {"symbol": "LINK/USDT", "last": 14.33, "volume": 65245939.1618, "change": 5.756}, {"symbol": "ONG/USDT", "last": 0.3404, "volume": 1483150.0002, "change": 7.722}, {"symbol": "HOT/USDT", "last": 0.002114, "volume": 11094010.967524, "change": 9.082}, {"symbol": "ZIL/USDT", "last": 0.01927, "volume": 19344596.460734, "change": 13.956}, {"symbol": "ZRX/USDT", "last": 0.3778, "volume": 3416534.3923, "change": 5.945}, {"symbol": "FET/USDT", "last": 1.303, "volume": 70596100.7786, "change": 4.659}, {"symbol": "BAT/USDT", "last": 0.2064, "volume": 3160906.7038, "change": 10.552}, {"symbol": "ZEC/USDT", "last": 41.17, "volume": 3796558.53757, "change": 7.888}, {"symbol": "IOST/USDT", "last": 0.006022, "volume": 5205111.056109, "change": 11.251}, {"symbol": "CELR/USDT", "last": 0.01461, "volume": 3763046.281971, "change": 10.264}, {"symbol": "DASH/USDT", "last": 28.98, "volume": 6567946.29093, "change": 10.865}, {"symbol": "THETA/USDT", "last": 1.505, "volume": 17396940.7836, "change": 14.015}, {"symbol": "ENJ/USDT", "last": 0.1763, "volume": 6939423.80651, "change": 13.742}, {"symbol": "ATOM/USDT", "last": 5.606, "volume": 31726607.78121, "change": 8.664}, {"symbol": "TFUEL/USDT", "last": 0.0612, "volume": 1893551.77966, "change": 7.975}, {"symbol": "ONE/USDT", "last": 0.0147, "volume": 3655731.579948, "change": 10.195}, {"symbol": "FTM/USDT", "last": 0.7453, "volume": 74795855.6268, "change": 3.643}, {"symbol": "ALGO/USDT", "last": 0.1982, "volume": 119010896.1124, "change": 21.446}, {"symbol": "DOGE/USDT", "last": 0.36907, "volume": 1818286205.91416, "change": 0.655}, {"symbol": "DUSK/USDT", "last": 0.1855, "volume": 4714236.4391, "change": 7.04}, {"symbol": "ANKR/USDT", "last": 0.0319, "volume": 5972628.316564, "change": 9.622}, {"symbol": "WIN/USDT", "last": 7.946e-05, "volume": 2531867.8073616, "change": 5.975}, {"symbol": "COS/USDT", "last": 0.007211, "volume": 2481731.7345663, "change": 4.72}, {"symbol": "MTL/USDT", "last": 1.163, "volume": 4599184.3112, "change": 7.685}, {"symbol": "DENT/USDT", "last": 0.00107, "volume": 3004148.269858, "change": 10.652}, {"symbol": "KEY/USDT", "last": 0.003646, "volume": 10188240.906989, "change": 2.387}, {"symbol": "CVC/USDT", "last": 0.1331, "volume": 2238131.69, "change": 6.822}, {"symbol": "CHZ/USDT", "last": 0.0716, "volume": 15237171.7887, "change": 9.648}, {"symbol": "BAND/USDT", "last": 1.33, "volume": 1481440.1103, "change": 9.827}, {"symbol": "XTZ/USDT", "last": 0.791, "volume": 4999029.9154, "change": 8.803}, {"symbol": "REN/USDT", "last": 0.03943, "volume": 3918494.00038, "change": 3.464}, {"symbol": "RVN/USDT", "last": 0.02177, "volume": 5029825.539031, "change": 9.068}, {"symbol": "HBAR/USDT", "last": 0.08809, "volume": 145838694.85719, "change": 28.523}, {"symbol": "NKN/USDT", "last": 0.0807, "volume": 3785948.5323, "change": 12.083}, {"symbol": "STX/USDT", "last": 1.947, "volume": 26042232.1863, "change": 5.643}, {"symbol": "KAVA/USDT", "last": 0.4117, "volume": 6469364.01255, "change": 6.437}, {"symbol": "ARPA/USDT", "last": 0.05305, "volume": 3561393.132402, "change": 5.994}, {"symbol": "IOTX/USDT", "last": 0.04139, "volume": 3254897.37687, "change": 4.626}, {"symbol": "RLC/USDT", "last": 1.72, "volume": 1482523.1368, "change": 4.623}, {"symbol": "CTXC/USDT", "last": 0.2537, "volume": 1585554.2515, "change": 6.507}, {"symbol": "BCH/USDT", "last": 447.7, "volume": 45483871.5489, "change": 3.634}, {"symbol": "TROY/USDT", "last": 0.004132, "volume": 18775664.927321, "change": 1.598}, {"symbol": "VITE/USDT", "last": 0.01431, "volume": 22936734.078722, "change": -8.854}, {"symbol": "FTT/USDT", "last": 1.9913, "volume": 23964277.448689, "change": 8.802}, {"symbol": "EUR/USDT", "last": 1.0583, "volume": 47231579.27997, "change": 0.351}, {"symbol": "OGN/USDT", "last": 0.1001, "volume": 1901446.1111, "change": 8.451}, {"symbol": "LSK/USDT", "last": 0.99, "volume": 1963373.3605, "change": 7.961}, {"symbol": "LTO/USDT", "last": 0.13, "volume": 4514271.2899, "change": 11.972}, {"symbol": "MBL/USDT", "last": 0.003134, "volume": 6713994.399785, "change": 5.309}, {"symbol": "COTI/USDT", "last": 0.10355, "volume": 5432815.36147, "change": 10.089}, {"symbol": "STPT/USDT", "last": 0.04654, "volume": 1530412.494904, "change": 5.437}, {"symbol": "DATA/USDT", "last": 0.03739, "volume": 1061360.437918, "change": 5.472}, {"symbol": "SOL/USDT", "last": 218.25, "volume": 1084347961.30618, "change": 2.196}, {"symbol": "CTSI/USDT", "last": 0.1502, "volume": 3986347.3001, "change": 9.395}, {"symbol": "HIVE/USDT", "last": 0.2431, "volume": 4211259.6096, "change": 5.284}, {"symbol": "CHR/USDT", "last": 0.2013, "volume": 8137641.9728, "change": 8.342}, {"symbol": "ARDR/USDT", "last": 0.09736, "volume": 1762468.56522, "change": 5.22}, {"symbol": "MDT/USDT", "last": 0.04469, "volume": 1428298.653259, "change": 4.27}, {"symbol": "STMX/USDT", "last": 0.006229, "volume": 2567771.395229, "change": 6.624}, {"symbol": "KNC/USDT", "last": 0.5303, "volume": 1539625.12224, "change": 7.37}, {"symbol": "LRC/USDT", "last": 0.1552, "volume": 10343354.5954, "change": 10.227}, {"symbol": "COMP/USDT", "last": 51.51, "volume": 2955302.03809, "change": 8.328}, {"symbol": "SC/USDT", "last": 0.005425, "volume": 7302425.150419, "change": 8.696}, {"symbol": "ZEN/USDT", "last": 9.28, "volume": 4554015.4802, "change": 6.057}, {"symbol": "SNX/USDT", "last": 1.654, "volume": 7406809.1216, "change": 9.175}, {"symbol": "VTHO/USDT", "last": 0.001873, "volume": 5375901.569837, "change": 8.706}, {"symbol": "DGB/USDT", "last": 0.00842, "volume": 23685744.011576, "change": 13.63}, {"symbol": "SXP/USDT", "last": 0.358, "volume": 6496993.91146, "change": 6.548}, {"symbol": "MKR/USDT", "last": 1499.0, "volume": 16324112.1122, "change": 3.237}, {"symbol": "STORJ/USDT", "last": 0.5007, "volume": 5270335.6709, "change": 9.395}, {"symbol": "MANA/USDT", "last": 0.4246, "volume": 44051884.815, "change": 23.862}, {"symbol": "YFI/USDT", "last": 6406.0, "volume": 4700076.63986, "change": 4.862}, {"symbol": "BAL/USDT", "last": 2.241, "volume": 1129174.74567, "change": 8.786}, {"symbol": "BLZ/USDT", "last": 0.1178, "volume": 2525191.0253, "change": 7.777}, {"symbol": "IRIS/USDT", "last": 0.01602, "volume": 9377512.806596, "change": 4.706}, {"symbol": "JST/USDT", "last": 0.03484, "volume": 3789583.318829, "change": 4.499}, {"symbol": "CRV/USDT", "last": 0.3109, "volume": 19651616.65135, "change": 8.63}, {"symbol": "SAND/USDT", "last": 0.3331, "volume": 39672316.2781, "change": 17.703}, {"symbol": "NMR/USDT", "last": 16.1, "volume": 2057257.9133, "change": 7.837}, {"symbol": "DOT/USDT", "last": 5.451, "volume": 69161263.50987, "change": 8.434}, {"symbol": "LUNA/USDT", "last": 0.5103, "volume": 104715850.004104, "change": 39.236}, {"symbol": "RSR/USDT", "last": 0.007228, "volume": 5537375.7794289, "change": 7.113}, {"symbol": "PAXG/USDT", "last": 2573.0, "volume": 4197877.0925, "change": -0.078}, {"symbol": "TRB/USDT", "last": 69.86, "volume": 28786576.01863, "change": 2.978}, {"symbol": "SUSHI/USDT", "last": 0.786, "volume": 6047141.9242, "change": 9.015}, {"symbol": "KSM/USDT", "last": 20.65, "volume": 4594515.64138, "change": 10.546}, {"symbol": "EGLD/USDT", "last": 30.29, "volume": 10309445.4694, "change": 6.169}, {"symbol": "DIA/USDT", "last": 0.7636, "volume": 2847945.73163, "change": 3.976}, {"symbol": "RUNE/USDT", "last": 5.662, "volume": 65412421.3379, "change": 1.561}, {"symbol": "FIO/USDT", "last": 0.03194, "volume": 4674785.30628, "change": 9.835}, {"symbol": "UMA/USDT", "last": 2.493, "volume": 3342249.8821, "change": 6.085}, {"symbol": "BEL/USDT", "last": 0.5867, "volume": 2186415.56513, "change": 6.421}, {"symbol": "WING/USDT", "last": 5.554, "volume": 3232366.64646, "change": 5.369}, {"symbol": "UNI/USDT", "last": 8.978, "volume": 53174299.95562, "change": 9.168}, {"symbol": "OXT/USDT", "last": 0.0756, "volume": 3369514.8219, "change": 11.34}, {"symbol": "SUN/USDT", "last": 0.02313, "volume": 15694485.13554, "change": 3.444}, {"symbol": "AVAX/USDT", "last": 35.45, "volume": 135547103.2176, "change": 9.11}, {"symbol": "FLM/USDT", "last": 0.0675, "volume": 1885941.4893, "change": 6.804}, {"symbol": "XVS/USDT", "last": 7.77, "volume": 5610610.3636, "change": 4.295}, {"symbol": "ALPHA/USDT", "last": 0.079, "volume": 3393201.0439, "change": 8.516}, {"symbol": "AAVE/USDT", "last": 168.74, "volume": 57186037.94708, "change": 7.622}, {"symbol": "NEAR/USDT", "last": 6.018, "volume": 183106502.053, "change": 9.737}, {"symbol": "FIL/USDT", "last": 4.457, "volume": 65969539.3188, "change": 8.973}, {"symbol": "INJ/USDT", "last": 25.3, "volume": 32803716.2088, "change": 6.481}, {"symbol": "AUDIO/USDT", "last": 0.1404, "volume": 4003108.3954, "change": 8.25}, {"symbol": "CTK/USDT", "last": 0.7197, "volume": 2325673.40014, "change": 3.823}, {"symbol": "AKRO/USDT", "last": 0.004161, "volume": 2708524.176937, "change": 5.209}, {"symbol": "AXS/USDT", "last": 5.68, "volume": 14458294.71059, "change": 10.959}, {"symbol": "HARD/USDT", "last": 0.1702, "volume": 9019072.0652, "change": -5.392}, {"symbol": "STRAX/USDT", "last": 0.05434, "volume": 1084902.03106, "change": 6.341}, {"symbol": "ROSE/USDT", "last": 0.08378, "volume": 10775363.514207, "change": 10.674}, {"symbol": "SKL/USDT", "last": 0.04144, "volume": 4072764.86953, "change": 9.168}, {"symbol": "GRT/USDT", "last": 0.2028, "volume": 24645252.2089, "change": 14.966}, {"symbol": "PSG/USDT", "last": 2.701, "volume": 1035060.81705, "change": 1.963}, {"symbol": "1INCH/USDT", "last": 0.3098, "volume": 4245862.01192, "change": 10.288}, {"symbol": "OG/USDT", "last": 5.262, "volume": 7096900.9012, "change": 3.217}, {"symbol": "ATM/USDT", "last": 1.99, "volume": 1046728.86766, "change": 2.051}, {"symbol": "ASR/USDT", "last": 2.088, "volume": 3402395.1239, "change": 0.675}, {"symbol": "CELO/USDT", "last": 0.6612, "volume": 9079401.68166, "change": 9.055}, {"symbol": "RIF/USDT", "last": 0.1128, "volume": 2366233.0364, "change": 9.728}, {"symbol": "TRU/USDT", "last": 0.0929, "volume": 35136832.0681, "change": 17.744}, {"symbol": "CKB/USDT", "last": 0.013201, "volume": 8000748.916896, "change": 4.961}, {"symbol": "TWT/USDT", "last": 0.9812, "volume": 6437157.3128, "change": 4.885}, {"symbol": "FIRO/USDT", "last": 1.284, "volume": 1371786.6851, "change": 5.941}, {"symbol": "LIT/USDT", "last": 0.705, "volume": 1341334.5983, "change": 7.306}, {"symbol": "SFP/USDT", "last": 0.6672, "volume": 1156995.0484, "change": 1.599}, {"symbol": "DODO/USDT", "last": 0.1251, "volume": 3594967.81307, "change": 5.214}, {"symbol": "CAKE/USDT", "last": 1.909, "volume": 12525516.80942, "change": 6.767}, {"symbol": "BADGER/USDT", "last": 3.265, "volume": 1702155.06476, "change": 5.698}, {"symbol": "FIS/USDT", "last": 0.3244, "volume": 1458400.3675, "change": 6.535}, {"symbol": "OM/USDT", "last": 2.3044, "volume": 265343094.925535, "change": 39.686}, {"symbol": "DEGO/USDT", "last": 2.057, "volume": 1183016.08367, "change": 8.951}, {"symbol": "ALICE/USDT", "last": 1.222, "volume": 7006596.132, "change": 11.293}, {"symbol": "LINA/USDT", "last": 0.004659, "volume": 2540554.012872, "change": 8.652}, {"symbol": "PERP/USDT", "last": 0.743, "volume": 2278265.840602, "change": 10.221}, {"symbol": "SUPER/USDT", "last": 1.3219, "volume": 8352046.4282, "change": 6.51}, {"symbol": "CFX/USDT", "last": 0.1532, "volume": 9985451.3584, "change": 5.51}, {"symbol": "TKO/USDT", "last": 0.3203, "volume": 1211300.97258, "change": 5.362}, {"symbol": "TLM/USDT", "last": 0.01188, "volume": 7009596.99862, "change": 11.759}, {"symbol": "BAR/USDT", "last": 2.102, "volume": 1252788.00591, "change": 2.989}, {"symbol": "BAKE/USDT", "last": 0.2615, "volume": 5227394.07663, "change": 5.444}, {"symbol": "BURGER/USDT", "last": 0.4265, "volume": 4015749.08856, "change": 6.042}, {"symbol": "SLP/USDT", "last": 0.002821, "volume": 5183390.251441, "change": 8.292}, {"symbol": "SHIB/USDT", "last": 2.474e-05, "volume": 277050522.5380323, "change": 3.299}, {"symbol": "ICP/USDT", "last": 9.353, "volume": 46956736.05993, "change": 14.662}, {"symbol": "AR/USDT", "last": 18.44, "volume": 29599937.5511, "change": 9.112}, {"symbol": "MASK/USDT", "last": 2.995, "volume": 10495546.9814, "change": 4.029}, {"symbol": "LPT/USDT", "last": 11.117, "volume": 6035966.57846, "change": 9.398}, {"symbol": "XVG/USDT", "last": 0.006229, "volume": 113508826.976848, "change": 22.042}, {"symbol": "ATA/USDT", "last": 0.0985, "volume": 1755033.8422, "change": 5.46}, {"symbol": "GTC/USDT", "last": 0.723, "volume": 1861950.0546, "change": 7.589}, {"symbol": "ERN/USDT", "last": 2.377, "volume": 1958265.0836, "change": 6.258}, {"symbol": "PHA/USDT", "last": 0.115, "volume": 3601799.7162, "change": 3.791}, {"symbol": "C98/USDT", "last": 0.1437, "volume": 3417640.60993, "change": 10.624}, {"symbol": "CLV/USDT", "last": 0.08723, "volume": 203481888.623885, "change": 114.377}, {"symbol": "QNT/USDT", "last": 70.5, "volume": 6617370.5071, "change": 13.71}, {"symbol": "FLOW/USDT", "last": 0.668, "volume": 12395376.10249, "change": 12.269}, {"symbol": "MINA/USDT", "last": 0.6734, "volume": 12320723.47104, "change": 7.865}, {"symbol": "RAY/USDT", "last": 4.824, "volume": 28301709.3889, "change": 1.987}, {"symbol": "ALPACA/USDT", "last": 0.1743, "volume": 3661877.21762, "change": 4.874}, {"symbol": "QUICK/USDT", "last": 0.04163, "volume": 1482984.53309, "change": 7.682}, {"symbol": "MBOX/USDT", "last": 0.1841, "volume": 19651383.84357, "change": 11.711}, {"symbol": "GHST/USDT", "last": 0.977, "volume": 13600874.3179, "change": 5.736}, {"symbol": "WAXP/USDT", "last": 0.0399, "volume": 2301270.07276, "change": 9.465}, {"symbol": "XEC/USDT", "last": 4.653e-05, "volume": 6856174.92422127, "change": 7.286}, {"symbol": "ELF/USDT", "last": 0.389, "volume": 1530382.96325, "change": 4.767}, {"symbol": "DYDX/USDT", "last": 1.2919, "volume": 21870436.802461, "change": 6.786}, {"symbol": "VIDT/USDT", "last": 0.03315, "volume": 4336548.3235, "change": 0.607}, {"symbol": "GALA/USDT", "last": 0.02843, "volume": 45580381.08441, "change": 10.666}, {"symbol": "ILV/USDT", "last": 41.98, "volume": 5987415.73731, "change": 9.694}, {"symbol": "YGG/USDT", "last": 0.5325, "volume": 10593677.09784, "change": 10.271}, {"symbol": "SYS/USDT", "last": 0.1081, "volume": 2128978.5519, "change": 9.969}, {"symbol": "FIDA/USDT", "last": 0.2157, "volume": 14663817.50594, "change": 3.354}, {"symbol": "AGLD/USDT", "last": 1.441, "volume": 12613734.8462, "change": -0.962}, {"symbol": "RAD/USDT", "last": 1.247, "volume": 3638453.2259, "change": 3.658}, {"symbol": "BETA/USDT", "last": 0.04511, "volume": 3779918.19208, "change": 2.897}, {"symbol": "RARE/USDT", "last": 0.1245, "volume": 5389805.44294, "change": 3.75}, {"symbol": "LAZIO/USDT", "last": 1.634, "volume": 1505838.91331, "change": 1.68}, {"symbol": "CHESS/USDT", "last": 0.1625, "volume": 2259592.01725, "change": 4.569}, {"symbol": "ADX/USDT", "last": 0.1788, "volume": 1255507.1466, "change": 2.818}, {"symbol": "AUCTION/USDT", "last": 14.29, "volume": 3488061.5344, "change": 5.383}, {"symbol": "DAR/USDT", "last": 0.15846, "volume": 6700694.82692, "change": 5.908}, {"symbol": "BNX/USDT", "last": 0.5519, "volume": 6106058.33523, "change": 3.449}, {"symbol": "MOVR/USDT", "last": 11.34, "volume": 4912071.293271, "change": 5.744}, {"symbol": "ENS/USDT", "last": 18.07, "volume": 19690101.5134, "change": 7.496}, {"symbol": "QI/USDT", "last": 0.01444, "volume": 1585150.09191, "change": 4.562}, {"symbol": "PORTO/USDT", "last": 1.799, "volume": 1137909.26033, "change": 2.158}, {"symbol": "POWR/USDT", "last": 0.247, "volume": 2140051.0994, "change": 8.144}, {"symbol": "JASMY/USDT", "last": 0.02197, "volume": 22892346.500508, "change": 7.014}, {"symbol": "AMP/USDT", "last": 0.004507, "volume": 10805346.310196, "change": 8.76}, {"symbol": "PYR/USDT", "last": 2.874, "volume": 2375387.145671, "change": 6.999}, {"symbol": "ALCX/USDT", "last": 20.45, "volume": 1992779.64414, "change": 13.359}, {"symbol": "SANTOS/USDT", "last": 4.161, "volume": 7696064.57438, "change": 1.315}, {"symbol": "BICO/USDT", "last": 0.2868, "volume": 5049411.270728, "change": 5.987}, {"symbol": "FLUX/USDT", "last": 0.5724, "volume": 2831375.039966, "change": 3.639}, {"symbol": "FXS/USDT", "last": 2.244, "volume": 2217220.2321, "change": 6.149}, {"symbol": "VOXEL/USDT", "last": 0.1659, "volume": 5401825.60523, "change": 7.379}, {"symbol": "HIGH/USDT", "last": 1.479, "volume": 5052719.908867, "change": 7.329}, {"symbol": "CVX/USDT", "last": 1.991, "volume": 1053738.809758, "change": 3.107}, {"symbol": "PEOPLE/USDT", "last": 0.06443, "volume": 61000428.995123, "change": 0.483}, {"symbol": "SPELL/USDT", "last": 0.0008639, "volume": 41398869.721269, "change": 15.448}, {"symbol": "JOE/USDT", "last": 0.3978, "volume": 2040694.966852, "change": 8.451}, {"symbol": "ACH/USDT", "last": 0.02335, "volume": 7189430.76495, "change": 9.214}, {"symbol": "IMX/USDT", "last": 1.348, "volume": 11332873.00165, "change": 10.764}, {"symbol": "GLMR/USDT", "last": 0.1836, "volume": 2438589.95151, "change": 9.091}, {"symbol": "LOKA/USDT", "last": 0.2042, "volume": 1637135.01557, "change": 7.587}, {"symbol": "API3/USDT", "last": 1.776, "volume": 9159441.61935, "change": 8.095}, {"symbol": "BTTC/USDT", "last": 1.14e-06, "volume": 6371527.51837919, "change": 5.556}, {"symbol": "ACA/USDT", "last": 0.0626, "volume": 2221382.778134, "change": 11.19}, {"symbol": "WOO/USDT", "last": 0.2581, "volume": 14568364.24577, "change": 6.301}, {"symbol": "ALPINE/USDT", "last": 1.416, "volume": 1467212.83642, "change": 3.132}, {"symbol": "T/USDT", "last": 0.02555, "volume": 1699898.808888, "change": 5.841}, {"symbol": "ASTR/USDT", "last": 0.062, "volume": 5655452.02076, "change": 8.202}, {"symbol": "GMT/USDT", "last": 0.1567, "volume": 8852923.82479, "change": 7.772}, {"symbol": "KDA/USDT", "last": 0.6598, "volume": 12898841.956411, "change": 9.04}, {"symbol": "APE/USDT", "last": 1.225, "volume": 54020402.83208, "change": 16.004}, {"symbol": "BSW/USDT", "last": 0.0646, "volume": 2063458.1219, "change": 6.076}, {"symbol": "STEEM/USDT", "last": 0.2066, "volume": 1807910.47645, "change": 8.565}, {"symbol": "NEXO/USDT", "last": 1.237, "volume": 3725188.96552, "change": 3.95}, {"symbol": "REI/USDT", "last": 0.05406, "volume": 4363855.566129, "change": 4.626}, {"symbol": "LDO/USDT", "last": 1.216, "volume": 20342210.74911, "change": 7.137}, {"symbol": "OP/USDT", "last": 1.682, "volume": 40614439.49949, "change": 9.008}, {"symbol": "LEVER/USDT", "last": 0.002071, "volume": 4853783.145994, "change": 10.043}, {"symbol": "STG/USDT", "last": 0.3256, "volume": 5816610.26375, "change": 5.338}, {"symbol": "LUNC/USDT", "last": 0.00011894, "volume": 69197068.32751429, "change": 19.442}, {"symbol": "GMX/USDT", "last": 28.27, "volume": 2928715.01307, "change": 3.477}, {"symbol": "POLYX/USDT", "last": 0.2954, "volume": 36809054.12274, "change": 20.13}, {"symbol": "APT/USDT", "last": 12.33, "volume": 106657417.6865, "change": 2.154}, {"symbol": "OSMO/USDT", "last": 0.4922, "volume": 1321917.966987, "change": 7.538}, {"symbol": "HFT/USDT", "last": 0.1582, "volume": 1231506.69765, "change": 8.06}, {"symbol": "PHB/USDT", "last": 1.796, "volume": 6038967.9106, "change": 4.358}, {"symbol": "HOOK/USDT", "last": 0.4104, "volume": 2821004.36, "change": 7.604}, {"symbol": "MAGIC/USDT", "last": 0.4013, "volume": 5868129.30015, "change": 9.945}, {"symbol": "HIFI/USDT", "last": 0.577, "volume": 3807673.23284, "change": 6.556}, {"symbol": "RPL/USDT", "last": 9.94, "volume": 2472761.5518, "change": 3.219}, {"symbol": "PROS/USDT", "last": 0.791, "volume": 39094492.9669, "change": -5.889}, {"symbol": "GNS/USDT", "last": 2.041, "volume": 1132686.15971, "change": 9.613}, {"symbol": "SYN/USDT", "last": 0.5799, "volume": 2509982.29016, "change": 9.498}, {"symbol": "VIB/USDT", "last": 0.0752, "volume": 4293927.7625, "change": 3.169}, {"symbol": "SSV/USDT", "last": 19.42, "volume": 10591762.98675, "change": 7.412}, {"symbol": "LQTY/USDT", "last": 1.08, "volume": 3282617.0596, "change": 0.465}, {"symbol": "AMB/USDT", "last": 0.00701, "volume": 3720060.21899, "change": 4.94}, {"symbol": "USTC/USDT", "last": 0.02506, "volume": 30453275.32161, "change": 13.138}, {"symbol": "GAS/USDT", "last": 5.03, "volume": 11590190.7989, "change": 16.193}, {"symbol": "GLM/USDT", "last": 0.3549, "volume": 2395142.19733, "change": 7.318}, {"symbol": "PROM/USDT", "last": 5.488, "volume": 1479249.047, "change": 4.434}, {"symbol": "ID/USDT", "last": 0.4473, "volume": 5754465.8537, "change": 7.112}, {"symbol": "ARB/USDT", "last": 0.6547, "volume": 81073773.85244, "change": 10.947}, {"symbol": "OAX/USDT", "last": 0.1688, "volume": 3297407.8841, "change": 3.053}, {"symbol": "RDNT/USDT", "last": 0.0581, "volume": 6048852.7151, "change": 6.998}, {"symbol": "WBTC/USDT", "last": 90586.91, "volume": 11797135.3966631, "change": 1.132}, {"symbol": "EDU/USDT", "last": 0.5377, "volume": 4405878.453, "change": 5.867}, {"symbol": "SUI/USDT", "last": 3.7413, "volume": 477298899.5202, "change": 10.243}, {"symbol": "AERGO/USDT", "last": 0.1147, "volume": 1157658.4245, "change": 7.297}, {"symbol": "PEPE/USDT", "last": 2.158e-05, "volume": 1339136027.683147, "change": 3.106}, {"symbol": "FLOKI/USDT", "last": 0.00024221, "volume": 354245007.23255104, "change": 9.483}, {"symbol": "AST/USDT", "last": 0.0873, "volume": 1452639.3505, "change": 3.929}, {"symbol": "SNT/USDT", "last": 0.0367, "volume": 10784703.93493, "change": 10.509}, {"symbol": "COMBO/USDT", "last": 0.4296, "volume": 1535654.01701, "change": 7.32}, {"symbol": "MAV/USDT", "last": 0.1819, "volume": 2254406.1678, "change": 7.126}, {"symbol": "PENDLE/USDT", "last": 5.414, "volume": 24569788.604, "change": 5.024}, {"symbol": "ARKM/USDT", "last": 2.105, "volume": 36976602.5045, "change": 2.383}, {"symbol": "WBETH/USDT", "last": 3339.96, "volume": 2882350.745482, "change": 2.624}, {"symbol": "WLD/USDT", "last": 2.348, "volume": 109693197.7532, "change": 4.124}, {"symbol": "FDUSD/USDT", "last": 1.0009, "volume": 797168324.5231, "change": -0.11}, {"symbol": "SEI/USDT", "last": 0.5316, "volume": 136311717.13649, "change": 17.067}, {"symbol": "CYBER/USDT", "last": 3.631, "volume": 5423184.78379, "change": 3.773}, {"symbol": "ARK/USDT", "last": 0.629, "volume": 3463102.8875, "change": 6.376}, {"symbol": "CREAM/USDT", "last": 17.6, "volume": 4969733.4204, "change": -2.331}, {"symbol": "GFT/USDT", "last": 0.01735, "volume": 3082330.39656, "change": 2.481}, {"symbol": "IQ/USDT", "last": 0.007199, "volume": 3817677.066263, "change": 7.4}, {"symbol": "NTRN/USDT", "last": 0.4422, "volume": 2902082.42995, "change": 9.131}, {"symbol": "TIA/USDT", "last": 5.167, "volume": 48183532.1302, "change": 6.977}, {"symbol": "MEME/USDT", "last": 0.01434, "volume": 52138151.41567, "change": 7.901}, {"symbol": "ORDI/USDT", "last": 39.31, "volume": 49772439.2487, "change": 2.637}, {"symbol": "BEAMX/USDT", "last": 0.02233, "volume": 13861672.2425, "change": 10.49}, {"symbol": "BLUR/USDT", "last": 0.2588, "volume": 10045975.92996, "change": 12.375}, {"symbol": "VANRY/USDT", "last": 0.1033, "volume": 9619266.2943, "change": 7.047}, {"symbol": "JTO/USDT", "last": 2.758, "volume": 14271323.31, "change": 0.474}, {"symbol": "1000SATS/USDT", "last": 0.0002538, "volume": 57169422.2983409, "change": 2.836}, {"symbol": "BONK/USDT", "last": 4.085e-05, "volume": 356200497.38893324, "change": 9.137}, {"symbol": "ACE/USDT", "last": 2.27, "volume": 5502266.3987, "change": 8.198}, {"symbol": "NFP/USDT", "last": 0.2563, "volume": 5567341.3812, "change": 10.189}, {"symbol": "AI/USDT", "last": 0.4995, "volume": 7337805.70406, "change": 10.46}, {"symbol": "XAI/USDT", "last": 0.2354, "volume": 10512590.89647, "change": 8.081}, {"symbol": "MANTA/USDT", "last": 0.828, "volume": 11275933.0243, "change": 9.091}, {"symbol": "ALT/USDT", "last": 0.11844, "volume": 13362768.10065, "change": 9.212}, {"symbol": "JUP/USDT", "last": 1.1287, "volume": 21055151.83047, "change": 2.693}, {"symbol": "PYTH/USDT", "last": 0.4229, "volume": 28421893.73486, "change": 2.745}, {"symbol": "RONIN/USDT", "last": 1.489, "volume": 5679295.56992, "change": 6.433}, {"symbol": "DYM/USDT", "last": 1.646, "volume": 5378910.8321, "change": 3.718}, {"symbol": "PIXEL/USDT", "last": 0.2172, "volume": 23427025.88126, "change": 14.799}, {"symbol": "STRK/USDT", "last": 0.4635, "volume": 19796981.316864, "change": 4.368}, {"symbol": "PORTAL/USDT", "last": 0.3404, "volume": 7451866.85488, "change": 11.863}, {"symbol": "PDA/USDT", "last": 0.04271, "volume": 4433876.618688, "change": 6.695}, {"symbol": "AXL/USDT", "last": 0.7359, "volume": 8979246.479099, "change": 9.836}, {"symbol": "WIF/USDT", "last": 3.717, "volume": 265630778.34868, "change": 3.221}, {"symbol": "METIS/USDT", "last": 46.2, "volume": 6787852.42241, "change": 8.706}, {"symbol": "AEVO/USDT", "last": 0.3649, "volume": 8673320.424535, "change": 8.44}, {"symbol": "BOME/USDT", "last": 0.010407, "volume": 140365796.95979, "change": 5.655}, {"symbol": "ETHFI/USDT", "last": 1.621, "volume": 22573134.5961, "change": 7.708}, {"symbol": "ENA/USDT", "last": 0.5462, "volume": 106796313.771722, "change": -1.621}, {"symbol": "W/USDT", "last": 0.244, "volume": 11172301.02699, "change": 5.628}, {"symbol": "TNSR/USDT", "last": 0.6349, "volume": 27196269.91055, "change": 5.535}, {"symbol": "SAGA/USDT", "last": 2.0396, "volume": 23297177.84835, "change": 4.152}, {"symbol": "TAO/USDT", "last": 528.9, "volume": 48970625.46301, "change": 4.032}, {"symbol": "OMNI/USDT", "last": 8.69, "volume": 6203786.5613, "change": 5.589}, {"symbol": "REZ/USDT", "last": 0.03892, "volume": 4015389.54508, "change": 5.446}, {"symbol": "BB/USDT", "last": 0.322, "volume": 8730844.70489, "change": 5.678}, {"symbol": "NOT/USDT", "last": 0.007642, "volume": 42254808.28752, "change": 4.143}, {"symbol": "IO/USDT", "last": 2.356, "volume": 28539788.95887, "change": 4.479}, {"symbol": "ZK/USDT", "last": 0.1474, "volume": 13316304.97506, "change": 6.734}, {"symbol": "LISTA/USDT", "last": 0.4286, "volume": 5419539.51227, "change": 9.672}, {"symbol": "ZRO/USDT", "last": 3.662, "volume": 14211726.01463, "change": 6.733}, {"symbol": "G/USDT", "last": 0.03084, "volume": 2056116.43611, "change": 4.613}, {"symbol": "BANANA/USDT", "last": 56.58, "volume": 8389198.62329, "change": 3.418}, {"symbol": "RENDER/USDT", "last": 6.999, "volume": 61990253.8049, "change": 4.525}, {"symbol": "TON/USDT", "last": 5.693, "volume": 55205053.81008, "change": 6.213}, {"symbol": "DOGS/USDT", "last": 0.0006486, "volume": 34706794.3795464, "change": 2.367}, {"symbol": "EURI/USDT", "last": 1.0582, "volume": 6781867.56364, "change": 0.322}, {"symbol": "SLF/USDT", "last": 0.3115, "volume": 2416619.66056, "change": 4.706}, {"symbol": "POL/USDT", "last": 0.42, "volume": 78659189.06967, "change": 12.873}, {"symbol": "NEIRO/USDT", "last": 0.00218112, "volume": 300655364.07998514, "change": 1.632}, {"symbol": "TURBO/USDT", "last": 0.009149, "volume": 40829047.640826, "change": 4.824}, {"symbol": "1MBABYDOGE/USDT", "last": 0.0025322, "volume": 28250723.602082, "change": 2.66}, {"symbol": "CATI/USDT", "last": 0.4405, "volume": 19420522.73374, "change": 6.84}, {"symbol": "HMSTR/USDT", "last": 0.004006, "volume": 46506886.406554, "change": -7.929}, {"symbol": "EIGEN/USDT", "last": 2.485, "volume": 20723695.42816, "change": 3.715}, {"symbol": "SCR/USDT", "last": 0.64, "volume": 9851866.8026, "change": 2.236}, {"symbol": "BNSOL/USDT", "last": 221.4, "volume": 2306195.6184, "change": 2.358}, {"symbol": "LUMIA/USDT", "last": 1.124, "volume": 11681728.7162, "change": 10.958}, {"symbol": "KAIA/USDT", "last": 0.1406, "volume": 8934678.58739, "change": 9.161}, {"symbol": "COW/USDT", "last": 0.3933, "volume": 19919293.9471, "change": 2.422}, {"symbol": "CETUS/USDT", "last": 0.3811, "volume": 25387476.81924, "change": 1.41}, {"symbol": "PNUT/USDT", "last": 1.7927, "volume": 1140527021.4635, "change": 1.231}, {"symbol": "ACT/USDT", "last": 0.7084, "volume": 305895707.52319, "change": -2.532}], "timestamp": 1731766475.212268}